{ "columns":0,
 "grid":
    {
     "height":1,
     "orientation":"orthogonal",
     "width":1
    },
 "margin":0,
 "name":"syndicate_vehicles",
 "spacing":0,
 "tilecount":3,
 "tiledversion":"1.4.3",
 "tileheight":56,
 "tileproperties":
    {
     "0":
        {
         "imagePositionX":"-56",
         "imagePositionY":"0",
         "object":"syndicate_dustkicker",
         "tilesetDirection":"right"
        },
     "1":
        {
         "imagePositionX":"-56",
         "imagePositionY":"0",
         "object":"syndicate_dustkicker-heavymissiles",
         "tilesetDirection":"right"
        },
     "2":
        {
         "imagePositionX":"-56",
         "imagePositionY":"0",
         "object":"syndicate_dustkicker-rockets",
         "tilesetDirection":"right"
        }
    },
 "tilepropertytypes":
    {
     "0":
        {
         "imagePositionX":"string",
         "imagePositionY":"string",
         "object":"string",
         "tilesetDirection":"string"
        },
     "1":
        {
         "imagePositionX":"string",
         "imagePositionY":"string",
         "object":"string",
         "tilesetDirection":"string"
        },
     "2":
        {
         "imagePositionX":"string",
         "imagePositionY":"string",
         "object":"string",
         "tilesetDirection":"string"
        }
    },
 "tiles":
    {
     "0":
        {
         "image":"..\/..\/..\/tiled\/syndicate\/objects\/vehicles\/syndicate_dustkicker.png",
         "imageheight":56,
         "imagewidth":120
        },
     "1":
        {
         "image":"..\/..\/..\/tiled\/syndicate\/objects\/vehicles\/syndicate_dustkicker-heavymissiles.png",
         "imageheight":56,
         "imagewidth":120
        },
     "2":
        {
         "image":"..\/..\/..\/tiled\/syndicate\/objects\/vehicles\/syndicate_dustkicker-rockets.png",
         "imageheight":56,
         "imagewidth":120
        }
    },
 "tilewidth":120,
 "type":"tileset",
 "version":1.1
}